stylo_metrix/__init__.py
stylo_metrix/stylo_metrix.py
stylo_metrix/utils.py
stylo_metrix/metrics/__init__.py
stylo_metrix/metrics/de/__init__.py
stylo_metrix/metrics/de/descriptive.py
stylo_metrix/metrics/de/grammatical_forms.py
stylo_metrix/metrics/de/graphical.py
stylo_metrix/metrics/de/inflection.py
stylo_metrix/metrics/de/lexical.py
stylo_metrix/metrics/de/punctuation.py
stylo_metrix/metrics/de/syntactic.py
stylo_metrix/metrics/de/data/__init__.py
stylo_metrix/metrics/de/data/dictionaries.py
stylo_metrix/metrics/en/__init__.py
stylo_metrix/metrics/en/detailed_lexical.py
stylo_metrix/metrics/en/detailed_tenses.py
stylo_metrix/metrics/en/grammar_en.py
stylo_metrix/metrics/en/hurtlex.py
stylo_metrix/metrics/en/lexical_en.py
stylo_metrix/metrics/en/parts_of_speech_en.py
stylo_metrix/metrics/en/social_media.py
stylo_metrix/metrics/en/syntactic_en.py
stylo_metrix/metrics/en/text_statistics.py
stylo_metrix/metrics/en/data/hurtlex/animals.txt
stylo_metrix/metrics/en/data/hurtlex/cognitive_disabilities.txt
stylo_metrix/metrics/en/data/hurtlex/deadly_sins.txt
stylo_metrix/metrics/en/data/hurtlex/derogatory_words.txt
stylo_metrix/metrics/en/data/hurtlex/disabilities.txt
stylo_metrix/metrics/en/data/hurtlex/economic_disadvantage.txt
stylo_metrix/metrics/en/data/hurtlex/ethnic_slurs.txt
stylo_metrix/metrics/en/data/hurtlex/felonies.txt
stylo_metrix/metrics/en/data/hurtlex/female_genetalia.txt
stylo_metrix/metrics/en/data/hurtlex/homosexuality.txt
stylo_metrix/metrics/en/data/hurtlex/locations.txt
stylo_metrix/metrics/en/data/hurtlex/male_genetalia.txt
stylo_metrix/metrics/en/data/hurtlex/moral.txt
stylo_metrix/metrics/en/data/hurtlex/plants.txt
stylo_metrix/metrics/en/data/hurtlex/potential.txt
stylo_metrix/metrics/en/data/hurtlex/professions.txt
stylo_metrix/metrics/en/data/hurtlex/prostitution.txt
stylo_metrix/metrics/pl/__init__.py
stylo_metrix/metrics/pl/descriptive.py
stylo_metrix/metrics/pl/grammatical_forms.py
stylo_metrix/metrics/pl/graphical.py
stylo_metrix-0.1.9.1.dist-info/LICENSE
stylo_metrix-0.1.9.1.dist-info/METADATA
stylo_metrix-0.1.9.1.dist-info/WHEEL
stylo_metrix-0.1.9.1.dist-info/top_level.txt
stylo_metrix-0.1.9.1.dist-info/RECORD
