Metadata-Version: 2.1
Name: stylo_metrix
Version: 0.1.9.1
Summary: StyloMetrix tool
Home-page: https://github.com/ZILiAT-NASK/StyloMetrix
Author: ZILiAT-NASK
Author-email: ziliat@nask.pl
Classifier: Programming Language :: Python :: 3
Classifier: License :: OSI Approved :: GNU General Public License v3 (GPLv3)
Classifier: Operating System :: OS Independent
Requires-Python: >=3.6
License-File: LICENSE
Requires-Dist: colorama
Requires-Dist: confection
Requires-Dist: emoji
Requires-Dist: morfeusz2
Requires-Dist: numpy
Requires-Dist: pandas
Requires-Dist: scikit-learn
Requires-Dist: scipy
Requires-Dist: spacy ==3.7.2
Requires-Dist: spacymoji
Requires-Dist: srsly
Requires-Dist: thinc
Requires-Dist: tqdm
Requires-Dist: spacy-syllables
Requires-Dist: pexpect
